lark_action/__init__.py
lark_action/__main__.py
lark_action/lark_action_raw.py
lark_action-0.1.5.dist-info/LICENSE
lark_action-0.1.5.dist-info/METADATA
lark_action-0.1.5.dist-info/WHEEL
lark_action-0.1.5.dist-info/entry_points.txt
lark_action-0.1.5.dist-info/top_level.txt
lark_action-0.1.5.dist-info/RECORD
