Metadata-Version: 2.1
Name: lark-action
Version: 0.1.5
Summary: UNKNOWN
Home-page: https://github.com/thautwarm/lark-action
Author: thautwarm
Author-email: twshere@outlook.com
License: mit
Platform: any
Classifier: Programming Language :: Python :: 3.6
Classifier: Programming Language :: Python :: 3.7
Classifier: Programming Language :: Python :: 3.8
Classifier: Programming Language :: Python :: 3.9
Classifier: Programming Language :: Python :: 3.10
Classifier: Programming Language :: Python :: Implementation :: CPython
Requires-Python: >=3.6.0
Requires-Dist: wisepy2 (>=1.1.1)
Requires-Dist: lark
